{"courseOfferings":[{"offeringUnit":{"code":"01"},"course":{"subject":"175","number":"202"},"supplementCode":"  ","campusCode":"NB","synopsisUrl":"https://www.cinemastudies.rutgers.edu/academics/undergraduate-students/course-descriptions","courseNotes":null,"unitNotes":null,"subjectNotes":null,"subjectGroupNotes":null,"prereqNotes":null,"coreCodes":"Arts and Literatures (AHp), SOE Only: Approved Humanities/Social Science (SOEHS)","title":"INTRO TO FILM II","fullTitle":"INTRODUCTION TO FILM II                                                         ","credits":"3","sections":[{"yearterm":"20251","registrationIndex":"10274","legendKey":null,"sectionNumber":"01","sectionNotes":null,"subtitleText":"INTRO TO FILM 2                         ","subtopicText":null,"sectionEligibility":null,"examCode":"C","sessionDates":null,"open":false,"sectionCourseType":"T","specialPermissionAdd":null,"comments":["Go to http://canvas.rutgers.edu"],"meetingTimes":[{"baClassHours":"","meetingDay":"Monday","startMinute":"840","endMinute":"920","buildingCode":"MU","buildingNum":"3011","roomNumber":"301","meetingModeCode":"02","meetingModeDesc":"LEC","campusAbbrev":"College Avenue","campusName":"College Avenue","campusLocation":"1"},{"baClassHours":"","meetingDay":"Wednesday","startMinute":"840","endMinute":"920","buildingCode":"MU","buildingNum":"3011","roomNumber":"301","meetingModeCode":"02","meetingModeDesc":"LEC","campusAbbrev":"College Avenue","campusName":"College Avenue","campusLocation":"1"},{"baClassHours":"","meetingDay":"Monday","startMinute":"1060","endMinute":"1240","buildingCode":"MU","buildingNum":"3011","roomNumber":"301","meetingModeCode":"28","meetingModeDesc":"FILM","campusAbbrev":"College Avenue","campusName":"College Avenue","campusLocation":"1"}],"instructors":[{"name":"FRESKO, DAVID"}],"crossListedSections":[],"majors":[]}]},{"offeringUnit":{"code":"01"},"course":{"subject":"175","number":"266"},"supplementCode":"  ","campusCode":"NB","synopsisUrl":"https://www.cinemastudies.rutgers.edu/academics/undergraduate-students/course-descriptions","courseNotes":null,"unitNotes":null,"subjectNotes":null,"subjectGroupNotes":null,"prereqNotes":null,"coreCodes":null,"title":"CULT FILMS AM CULTUR","fullTitle":"CULT FILMS IN AMERICAN CULTURE                                                  ","credits":"3","sections":[{"yearterm":"20251","registrationIndex":"09326","legendKey":null,"sectionNumber":"01","sectionNotes":null,"subtitleText":"CULT FILMS IN AMERICAN CULTURE          ","subtopicText":null,"sectionEligibility":null,"examCode":"C","sessionDates":null,"open":true,"sectionCourseType":"T","specialPermissionAdd":null,"comments":[],"meetingTimes":[{"baClassHours":"","meetingDay":"Tuesday","startMinute":"1060","endMinute":"1140","buildingCode":"RAB","buildingNum":"8303","roomNumber":"001","meetingModeCode":"02","meetingModeDesc":"LEC","campusAbbrev":"C/D","campusName":"C/D","campusLocation":"4"},{"baClassHours":"","meetingDay":"Thursday","startMinute":"1060","endMinute":"1140","buildingCode":"RAB","buildingNum":"8303","roomNumber":"001","meetingModeCode":"02","meetingModeDesc":"LEC","campusAbbrev":"C/D","campusName":"C/D","campusLocation":"4"},{"baClassHours":"","meetingDay":"Thursday","startMinute":"1170","endMinute":"1250","buildingCode":"RAB","buildingNum":"8303","roomNumber":"001","meetingModeCode":"28","meetingModeDesc":"FILM","campusAbbrev":"C/D","campusName":"C/D","campusLocation":"4"}],"instructors":[{"name":"NIGRIN, ALBERT"}],"crossListedSections":[{"course":"01:050:266:01"}],"majors":[]}]},{"offeringUnit":{"code":"01"},"course":{"subject":"175","number":"306"},"supplementCode":"  ","campusCode":"NB","synopsisUrl":"https://www.cinemastudies.rutgers.edu/academics/undergraduate-students/course-descriptions","courseNotes":null,"unitNotes":null,"subjectNotes":null,"subjectGroupNotes":null,"prereqNotes":null,"coreCodes":"Arts and Literatures (AHp), SOE Only: Approved Humanities/Social Science (SOEHS)","title":"MOD FRENCH CINEMA","fullTitle":"MODERN FRENCH CINEMA (IN ENGLISH)                                               ","credits":"3","sections":[{"yearterm":"20251","registrationIndex":"10275","legendKey":null,"sectionNumber":"01","sectionNotes":null,"subtitleText":"MODERN FRENCH CINEMA                    ","subtopicText":null,"sectionEligibility":null,"examCode":"C","sessionDates":null,"open":true,"sectionCourseType":"T","specialPermissionAdd":null,"comments":[],"meetingTimes":[{"baClassHours":"","meetingDay":"Tuesday","startMinute":"840","endMinute":"920","buildingCode":"ABW","buildingNum":"3198","roomNumber":"4140","meetingModeCode":"02","meetingModeDesc":"LEC","campusAbbrev":"College Avenue","campusName":"College Avenue","campusLocation":"1"},{"baClassHours":"","meetingDay":"Thursday","startMinute":"840","endMinute":"920","buildingCode":"ABW","buildingNum":"3198","roomNumber":"4140","meetingModeCode":"02","meetingModeDesc":"LEC","campusAbbrev":"College Avenue","campusName":"College Avenue","campusLocation":"1"}],"instructors":[{"name":"SWENSON, JAMES"}],"crossListedSections":[{"course":"01:420:471:01"},{"course":"01:420:306:01"}],"majors":[]}]},{"offeringUnit":{"code":"01"},"course":{"subject":"175","number":"315"},"supplementCode":"  ","campusCode":"NB","synopsisUrl":"https://www.cinemastudies.rutgers.edu/academics/undergraduate-students/course-descriptions","courseNotes":null,"unitNotes":null,"subjectNotes":null,"subjectGroupNotes":null,"prereqNotes":null,"coreCodes":null,"title":"AMERICAN CINEMA I","fullTitle":"AMERICAN CINEMA I                                                               ","credits":"3","sections":[{"yearterm":"20251","registrationIndex":"10278","legendKey":null,"sectionNumber":"01","sectionNotes":null,"subtitleText":null,"subtopicText":null,"sectionEligibility":null,"examCode":"C","sessionDates":null,"open":true,"sectionCourseType":"T","specialPermissionAdd":null,"comments":[],"meetingTimes":[{"baClassHours":"","meetingDay":"Monday","startMinute":"620","endMinute":"700","buildingCode":"MU","buildingNum":"3011","roomNumber":"301","meetingModeCode":"02","meetingModeDesc":"LEC","campusAbbrev":"College Avenue","campusName":"College Avenue","campusLocation":"1"},{"baClassHours":"","meetingDay":"Thursday","startMinute":"620","endMinute":"700","buildingCode":"MU","buildingNum":"3011","roomNumber":"301","meetingModeCode":"02","meetingModeDesc":"LEC","campusAbbrev":"College Avenue","campusName":"College Avenue","campusLocation":"1"},{"baClassHours":"","meetingDay":"Tuesday","startMinute":"1060","endMinute":"1240","buildingCode":"MU","buildingNum":"3011","roomNumber":"301","meetingModeCode":"28","meetingModeDesc":"FILM","campusAbbrev":"College Avenue","campusName":"College Avenue","campusLocation":"1"}],"instructors":[{"name":"GINSBERG, TERRI"}],"crossListedSections":[],"majors":[]}]},{"offeringUnit":{"code":"01"},"course":{"subject":"175","number":"321"},"supplementCode":"  ","campusCode":"NB","synopsisUrl":"https://www.cinemastudies.rutgers.edu/academics/undergraduate-students/course-descriptions","courseNotes":null,"unitNotes":null,"subjectNotes":null,"subjectGroupNotes":null,"prereqNotes":null,"coreCodes":"Arts and Literatures (AHp), Diversities and Social Inequalities (CCD), SOE Only: Approved Humanities/Social Science (SOEHS)","title":"WORLD CINEMA II","fullTitle":"WORLD CINEMA II","credits":"3","sections":[{"yearterm":"20251","registrationIndex":"10279","legendKey":null,"sectionNumber":"01","sectionNotes":null,"subtitleText":"WORLD CINEMA II                         ","subtopicText":null,"sectionEligibility":null,"examCode":"C","sessionDates":null,"open":true,"sectionCourseType":"T","specialPermissionAdd":null,"comments":["Go to http://canvas.rutgers.edu"],"meetingTimes":[{"baClassHours":"","meetingDay":"Tuesday","startMinute":"620","endMinute":"700","buildingCode":"ABE","buildingNum":"3198","roomNumber":"1180","meetingModeCode":"02","meetingModeDesc":"LEC","campusAbbrev":"College Avenue","campusName":"College Avenue","campusLocation":"1"},{"baClassHours":"","meetingDay":"Friday","startMinute":"620","endMinute":"700","buildingCode":"ABE","buildingNum":"3198","roomNumber":"1180","meetingModeCode":"02","meetingModeDesc":"LEC","campusAbbrev":"College Avenue","campusName":"College Avenue","campusLocation":"1"},{"baClassHours":"","meetingDay":"Thursday","startMinute":"1060","endMinute":"1240","buildingCode":"MI","buildingNum":"3010","roomNumber":"100","meetingModeCode":"28","meetingModeDesc":"FILM","campusAbbrev":"College Avenue","campusName":"College Avenue","campusLocation":"1"}],"instructors":[{"name":"MARTIN-MARQUEZ"}],"crossListedSections":[],"majors":[]}]},{"offeringUnit":{"code":"01"},"course":{"subject":"175","number":"370"},"supplementCode":"  ","campusCode":"NB","synopsisUrl":"https://www.cinemastudies.rutgers.edu/academics/undergraduate-students/course-descriptions","courseNotes":null,"unitNotes":null,"subjectNotes":null,"subjectGroupNotes":null,"prereqNotes":null,"coreCodes":null,"title":"FILM GENRES","fullTitle":"FILM GENRES                                                                     ","credits":"3","sections":[{"yearterm":"20251","registrationIndex":"10280","legendKey":null,"sectionNumber":"01","sectionNotes":null,"subtitleText":null,"subtopicText":null,"sectionEligibility":null,"examCode":"C","sessionDates":null,"open":true,"sectionCourseType":"T","specialPermissionAdd":null,"comments":[],"meetingTimes":[{"baClassHours":"","meetingDay":"Monday","startMinute":"730","endMinute":"810","buildingCode":"ABW","buildingNum":"3198","roomNumber":"4140","meetingModeCode":"02","meetingModeDesc":"LEC","campusAbbrev":"College Avenue","campusName":"College Avenue","campusLocation":"1"},{"baClassHours":"","meetingDay":"Thursday","startMinute":"730","endMinute":"810","buildingCode":"ABW","buildingNum":"3198","roomNumber":"4140","meetingModeCode":"02","meetingModeDesc":"LEC","campusAbbrev":"College Avenue","campusName":"College Avenue","campusLocation":"1"}],"instructors":[{"name":"GINSBERG, TERRI"}],"crossListedSections":[],"majors":[]}]},{"offeringUnit":{"code":"01"},"course":{"subject":"175","number":"377"},"supplementCode":"  ","campusCode":"NB","synopsisUrl":"https://www.cinemastudies.rutgers.edu/academics/undergraduate-students/course-descriptions","courseNotes":null,"unitNotes":null,"subjectNotes":null,"subjectGroupNotes":null,"prereqNotes":null,"coreCodes":null,"title":"TPCS IN WORLD CINEMA","fullTitle":"TPCS IN WORLD CINEMA","credits":"3","sections":[{"yearterm":"20251","registrationIndex":"10281","legendKey":null,"sectionNumber":"01","sectionNotes":null,"subtitleText":"MAFIA MOVIES                            ","subtopicText":null,"sectionEligibility":null,"examCode":"C","sessionDates":null,"open":true,"sectionCourseType":"T","specialPermissionAdd":null,"comments":["Go to http://canvas.rutgers.edu"],"meetingTimes":[{"baClassHours":"","meetingDay":"Monday","startMinute":"730","endMinute":"810","buildingCode":"HH","buildingNum":"3119","roomNumber":"B2","meetingModeCode":"02","meetingModeDesc":"LEC","campusAbbrev":"College Avenue","campusName":"College Avenue","campusLocation":"1"},{"baClassHours":"","meetingDay":"Thursday","startMinute":"730","endMinute":"810","buildingCode":"HH","buildingNum":"3119","roomNumber":"B2","meetingModeCode":"02","meetingModeDesc":"LEC","campusAbbrev":"College Avenue","campusName":"College Avenue","campusLocation":"1"}],"instructors":[{"name":"SCALIA, ROSARIO"}],"crossListedSections":[{"course":"01:560:320:01"}],"majors":[]},{"yearterm":"20251","registrationIndex":"10284","legendKey":null,"sectionNumber":"03","sectionNotes":null,"subtitleText":"EASTERN EUROPEAN CINEMA                 ","subtopicText":null,"sectionEligibility":null,"examCode":"U","sessionDates":null,"open":true,"sectionCourseType":"T","specialPermissionAdd":null,"comments":[],"meetingTimes":[{"baClassHours":"","meetingDay":"Monday","startMinute":"950","endMinute":"1030","buildingCode":"HH","buildingNum":"3119","roomNumber":"A1","meetingModeCode":"02","meetingModeDesc":"LEC","campusAbbrev":"College Avenue","campusName":"College Avenue","campusLocation":"1"},{"baClassHours":"","meetingDay":"Wednesday","startMinute":"950","endMinute":"1030","buildingCode":"HH","buildingNum":"3119","roomNumber":"A1","meetingModeCode":"02","meetingModeDesc":"LEC","campusAbbrev":"College Avenue","campusName":"College Avenue","campusLocation":"1"}],"instructors":[{"name":"ZAPASNIK, KAMIL"}],"crossListedSections":[{"course":"01:860:337:01"},{"course":"01:195:395:02"}],"majors":[]}]},{"offeringUnit":{"code":"01"},"course":{"subject":"175","number":"398"},"supplementCode":"  ","campusCode":"NB","synopsisUrl":"https://www.cinemastudies.rutgers.edu/academics/undergraduate-students/course-descriptions","courseNotes":null,"unitNotes":null,"subjectNotes":null,"subjectGroupNotes":null,"prereqNotes":null,"coreCodes":"Non-Core: Community Engagement (CE)","title":"INTERNSHP CINEMA STD","fullTitle":"INTERNSHIP IN CINEMA STUDIES                                                    ","credits":"3","sections":[{"yearterm":"20251","registrationIndex":"10287","legendKey":null,"sectionNumber":"01","sectionNotes":null,"subtitleText":"INTERNSHIP                              ","subtopicText":null,"sectionEligibility":null,"examCode":"O","sessionDates":null,"open":true,"sectionCourseType":"T","specialPermissionAdd":" Department staff","comments":["Go to http://canvas.rutgers.edu"],"meetingTimes":[{"baClassHours":"B","meetingDay":null,"startMinute":null,"endMinute":null,"buildingCode":"","buildingNum":null,"roomNumber":"","meetingModeCode":"28","meetingModeDesc":"FILM","campusAbbrev":"","campusName":"","campusLocation":""}],"instructors":[{"name":"NIGRIN, ALBERT"}],"crossListedSections":[],"majors":[]}]},{"offeringUnit":{"code":"01"},"course":{"subject":"175","number":"425"},"supplementCode":"  ","campusCode":"NB","synopsisUrl":"https://www.cinemastudies.rutgers.edu/academics/undergraduate-students/course-descriptions","courseNotes":null,"unitNotes":null,"subjectNotes":null,"subjectGroupNotes":null,"prereqNotes":"(01:355:101 )<em> OR </em>(01:355:103 )<em> OR </em>(01:355:104 )","coreCodes":"Writing and Communication in a Discipline (WCd)","title":"SENIOR SEMINAR","fullTitle":"SENIOR SEMINAR IN CINEMA STUDIES                                                ","credits":"3","sections":[{"yearterm":"20251","registrationIndex":"10288","legendKey":null,"sectionNumber":"01","sectionNotes":"FOR SPECIAL PERMISSION NUMBER NINA.ECHEVERRIA@RUTGERS.EDU  ","subtitleText":"SENIOR SEMINAR                          ","subtopicText":null,"sectionEligibility":null,"examCode":"C","sessionDates":null,"open":true,"sectionCourseType":"T","specialPermissionAdd":" Department staff","comments":[],"meetingTimes":[{"baClassHours":"","meetingDay":"Monday","startMinute":"620","endMinute":"700","buildingCode":"ABW","buildingNum":"3198","roomNumber":"4140","meetingModeCode":"02","meetingModeDesc":"LEC","campusAbbrev":"College Avenue","campusName":"College Avenue","campusLocation":"1"},{"baClassHours":"","meetingDay":"Thursday","startMinute":"620","endMinute":"700","buildingCode":"ABW","buildingNum":"3198","roomNumber":"4140","meetingModeCode":"02","meetingModeDesc":"LEC","campusAbbrev":"College Avenue","campusName":"College Avenue","campusLocation":"1"},{"baClassHours":"","meetingDay":"Wednesday","startMinute":"1060","endMinute":"1240","buildingCode":"ABW","buildingNum":"3198","roomNumber":"4140","meetingModeCode":"28","meetingModeDesc":"FILM","campusAbbrev":"College Avenue","campusName":"College Avenue","campusLocation":"1"}],"instructors":[{"name":"FRESKO, DAVID"}],"crossListedSections":[],"majors":[]}]}]}